gscipy/__init__.py
gscipy/config.py
gscipy/csv_io.py
gscipy/decorators.py
gscipy/general.py
gscipy/json_io.py
gscipy/operators.py
gscipy/signals.py
gscipy/time.py
gscipy/trajectories.py
gscipy/utils.py
gscipy/vectors.py
gscipy/visualization.py
gscipy-0.1.4.dist-info/LICENSE.txt
gscipy-0.1.4.dist-info/METADATA
gscipy-0.1.4.dist-info/WHEEL
gscipy-0.1.4.dist-info/top_level.txt
gscipy-0.1.4.dist-info/RECORD
