Metadata-Version: 2.1
Name: gscipy
Version: 0.1.4
Summary: Gabba Scientific utilities
Author: Matteo Gabba
Author-email: m.gabba083@gmail.com
License: Mozilla Public License Version 2.0
Project-URL: repository, https://github.com/matteogabba/gspy.git
Keywords: gabba scientific
Classifier: Development Status :: 2 - Pre-Alpha
Requires-Python: >=3.10
License-File: LICENSE.txt
Requires-Dist: pandas
Requires-Dist: numpy
Requires-Dist: scipy
Requires-Dist: matplotlib
Requires-Dist: PyWavelets
Requires-Dist: more-itertools
Requires-Dist: statsmodels (>=0.13.5)
